{"expireTime":9007200903272267000,"key":"transformer-remark-markdown-html-ast-9caffbf33594b030f161d3b87e242600-gatsby-remark-external-linksgatsby-remark-imagesgatsby-remark-code-titlesgatsby-remark-prismjs-","val":{"type":"root","children":[{"type":"element","tagName":"ul","properties":{},"children":[{"type":"text","value":"\n"},{"type":"element","tagName":"li","properties":{},"children":[{"type":"text","value":"Collaborated with a team of researchers to standardize networking processes using OCaml","position":{"start":{"line":2,"column":3,"offset":3},"end":{"line":2,"column":90,"offset":90}}}],"position":{"start":{"line":2,"column":1,"offset":1},"end":{"line":2,"column":90,"offset":90}}},{"type":"text","value":"\n"},{"type":"element","tagName":"li","properties":{},"children":[{"type":"text","value":"Composed a pretty printer from Petr4 to Stdout ","position":{"start":{"line":3,"column":3,"offset":93},"end":{"line":3,"column":50,"offset":140}}}],"position":{"start":{"line":3,"column":1,"offset":91},"end":{"line":3,"column":50,"offset":140}}},{"type":"text","value":"\n"},{"type":"element","tagName":"li","properties":{},"children":[{"type":"text","value":"Designed and wrote a compiler from Petr4 to C","position":{"start":{"line":4,"column":3,"offset":143},"end":{"line":4,"column":48,"offset":188}}}],"position":{"start":{"line":4,"column":1,"offset":141},"end":{"line":4,"column":48,"offset":188}}},{"type":"text","value":"\n"}],"position":{"start":{"line":2,"column":1,"offset":1},"end":{"line":4,"column":48,"offset":188}}}],"position":{"start":{"line":1,"column":1,"offset":0},"end":{"line":4,"column":48,"offset":188}}}}